{
  "name": "apprendre",
  "description": "ou apprendre a programmer ?",
  "response": {
    "choice": {
      "python": {
        "embed": {
          "title": "Où apprendre le Python ?",
          "description": [
            "Vous voulez apprendre le Python ? Vous êtes au bon endroit !",
            "Sachez que aucun cours n'es parfait, et la chose la plus importante, c'est de s'entrainer ! Faites des minis-projets régulièrement, et testez régulièrement !",
            "Aussi, même si vous avez peu de connaissance, essayez d'aider ceux qui en ont encore moins, ça aide beaucoup à retenir !"
          ],
          "fields": [
            {
              "name": "__Cours français :__",
              "value": [
                "• [OpenClassroom](https://openclassrooms.com/fr/courses/235344-apprenez-a-programmer-en-python) (gratuit) : le cours est un peu ancien, mais il vous permettra d'acquérir de petites bases ! Pour apprendre des choses plus poussés, OpenClassroom n'est pas conseillé."
              ]
            },
            {
              "name": "__Cours anglais :__",
              "value": [
                "• [automatetheboringstuff](https://automatetheboringstuff.com/) (gratuit) : pour les tout nouveaux vis-à-vis de la programmation",
                "• [learnxinyminutes](https://learnxinyminutes.com/docs/python3/) (gratuit) : pour ceux qui savent déjà programmer",
                "• [python](https://docs.python.org/3/tutorial/) (gratuit) : le tutoriel officiel",
                "• [w3school](https://www.w3schools.com/python/python_intro.asp) (gratuit) : un bon cours"
              ]
            }
          ]
        }
      },
      "javascript": {
        "embed": {
          "title": "Où apprendre le JavaScript ?",
          "description": [
            "Vous voulez apprendre le JavaScript ? Vous êtes au bon endroit !",
            "Sachez que aucun cours n'es parfait, et la chose la plus importante, c'est de s'entrainer ! Faites des minis-projets régulièrement, et testez régulièrement !",
            "Aussi, même si vous avez peu de connaissance, essayez d'aider ceux qui en ont encore moins, ça aide beaucoup à retenir !"
          ],
          "fields": [
            {
              "name": "__Cours anglais :__",
              "value": [
                "• [w3school](https://www.w3schools.com/js/default.asp) (gratuit) : un très bon cours",
                "• [mozilla.org]( https://developer.mozilla.org/fr/docs/Web/JavaScript/) (gratuit) : le cours officiel pour apprendre le javascript"
              ]
            }
          ]
        }
      },
      "html/css": {
        "embed": {
          "title": "Où apprendre le HTML/CSS ?",
          "description": [
            "Vous voulez apprendre le HTML/CSS ? Vous êtes au bon endroit !",
            "Sachez que aucun cours n'es parfait, et la chose la plus importante, c'est de s'entrainer ! Faites des minis-projets régulièrement, et testez régulièrement !",
            "Aussi, même si vous avez peu de connaissance, essayez d'aider ceux qui en ont encore moins, ça aide beaucoup à retenir !"
          ],
          "fields": [
            {
              "name": "__Cours français :__",
              "value": [
                "• [OpenClassroom](https://openclassrooms.com/fr/courses/1603881-apprenez-a-creer-votre-site-web-avec-html5-et-css3/6725196-entrainez-vous-en-structurant-votre-cv) (gratuit) : un excellent cours !"
              ]
            },
            {
              "name": "__Cours anglais :__",
              "value": [
                "• [w3school](https://www.w3schools.com/html/default.asp) (gratuit) : un cours pour le HTML",
                "• [w3school](https://www.w3schools.com/css/default.asp) (gratuit) : un cours pour le CSS"
              ]
            }
          ]
        }
      }
    }
  }
}